area_attention/__init__.py
area_attention/area_attention.py
area_attention/multi_head_area_attention.py
area_attention-0.1.0.dist-info/LICENSE
area_attention-0.1.0.dist-info/METADATA
area_attention-0.1.0.dist-info/WHEEL
area_attention-0.1.0.dist-info/top_level.txt
area_attention-0.1.0.dist-info/RECORD
